textxdev/__init__.py
textxdev/cli/__init__.py
textxdev/cli/startproject.py
textxdev/scaffold/__init__.py
textxdev/scaffold/project.que
textxdev/scaffold/template/.gitignore
textxdev/scaffold/template/CHANGELOG.md.jinja
textxdev/scaffold/template/LICENSE.jinja
textxdev/scaffold/template/PULL_REQUEST_TEMPLATE.md
textxdev/scaffold/template/README.md.jinja
textxdev/scaffold/template/install-dev.sh
textxdev/scaffold/template/install-test.sh
textxdev/scaffold/template/pyproject.toml.jinja
textxdev/scaffold/template/runtests.sh.jinja
textxdev/scaffold/template/.github/workflows/ci-linux-ubuntu.yml.jinja
textxdev/scaffold/template/__gen____package__/__init__.py.jinja
textxdev/scaffold/template/__lang____package__/__init__.py.jinja
textxdev/scaffold/template/__lang____package__/__language__.tx
textxdev/scaffold/template/tests/.dummy
textx_dev-0.2.0.dist-info/entry_points.txt
textx_dev-0.2.0.dist-info/licenses/LICENSE
textx_dev-0.2.0.dist-info/WHEEL
textx_dev-0.2.0.dist-info/METADATA
textx_dev-0.2.0.dist-info/RECORD
